azuremlconstructor/__init__.py
azuremlconstructor/__main__.py
azuremlconstructor/_utils.py
azuremlconstructor/core.py
azuremlconstructor/exceptions.py
azuremlconstructor/input.py
azuremlconstructor/schemas.py
azuremlconstructor/utils.py
azuremlconstructor/apply/__init__.py
azuremlconstructor/apply/apply.py
azuremlconstructor/confs/__init__.py
azuremlconstructor/confs/configs.py
azuremlconstructor/denv/__init__.py
azuremlconstructor/denv/denv.py
azuremlconstructor/denv/dot_env_loader.py
azuremlconstructor/init/__init__.py
azuremlconstructor/init/args_handling.py
azuremlconstructor/init/init.py
azuremlconstructor/init/init_structure.py
azuremlconstructor/rename/__init__.py
azuremlconstructor/rename/rename.py
azuremlconstructor/run/__init__.py
azuremlconstructor/run/run.py
azuremlconstructor/src/__init__.py
azuremlconstructor/src/templates/apply/aml
azuremlconstructor/src/templates/apply/data_loaders
azuremlconstructor/src/templates/apply/script
azuremlconstructor/src/templates/init/conda_dependencies
azuremlconstructor/src/templates/init/dot_amlignore
azuremlconstructor/src/templates/init/dot_env
azuremlconstructor/src/templates/init/env_vars
azuremlconstructor/src/templates/init/settings
azuremlconstructor/tests/__init__.py
azuremlconstructor/tests/apply/__init__.py
azuremlconstructor/tests/apply/test_apply_path.py
azuremlconstructor/tests/core/__init__.py
azuremlconstructor/tests/init/__init__.py
azuremlconstructor/tests/init/test_env_bank.py
azuremlconstructor/tests/run/__init__.py
azuremlconstructor/tests/src/templates/settings
azuremlconstructor/update/__init__.py
azuremlconstructor/update/update.py
azuremlconstructor-0.0.4.dist-info/LICENSE
azuremlconstructor-0.0.4.dist-info/WHEEL
azuremlconstructor-0.0.4.dist-info/METADATA
azuremlconstructor-0.0.4.dist-info/RECORD
